coreugate/__init__.py
coreugate/coreugate.py
coreugate/run.py
coreugate/utils/config.j2.yaml
coreugate/utils/main.nf
coreugate-2.0.4.dist-info/METADATA
coreugate-2.0.4.dist-info/WHEEL
coreugate-2.0.4.dist-info/entry_points.txt
coreugate-2.0.4.dist-info/top_level.txt
coreugate-2.0.4.dist-info/RECORD
