Metadata-Version: 2.1
Name: coreugate
Version: 2.0.4
Summary: calculate pair-wise allelic distances from cgMLST implements chewBBACAs
Home-page: https://github.com/kristyhoran/coreugate
Author: Kristy Horan
Author-email: kristyhoran15@gmail.com
License: UNKNOWN
Platform: UNKNOWN
Classifier: Programming Language :: Python :: 3.7
Classifier: Operating System :: OS Independent
Classifier: Development Status :: 4 - Beta
Classifier: Intended Audience :: Science/Research
Classifier: Topic :: Scientific/Engineering :: Bio-Informatics
Classifier: License :: OSI Approved :: GNU General Public License v3 (GPLv3)
Requires-Python: >=3.7
Requires-Dist: pytest
Requires-Dist: jinja2
Requires-Dist: pandas
Requires-Dist: numpy
Requires-Dist: sh
Requires-Dist: packaging
Requires-Dist: argparse
Provides-Extra: tests
Requires-Dist: pytest ; extra == 'tests'
Requires-Dist: flake8 ; extra == 'tests'
